mammopy/__init__.py
mammopy/analysis.py
mammopy/pre_process.py
mammopy/visualization.py
segmentation_models/__init__.py
segmentation_models/__version__.py
segmentation_models/base/__init__.py
segmentation_models/base/heads.py
segmentation_models/base/initialization.py
segmentation_models/base/model.py
segmentation_models/base/modules.py
segmentation_models/encoders/__init__.py
segmentation_models/encoders/_base.py
segmentation_models/encoders/_preprocessing.py
segmentation_models/encoders/_utils.py
segmentation_models/encoders/densenet.py
segmentation_models/encoders/dpn.py
segmentation_models/encoders/efficientnet.py
segmentation_models/encoders/inceptionresnetv2.py
segmentation_models/encoders/inceptionv4.py
segmentation_models/encoders/mobilenet.py
segmentation_models/encoders/resnet.py
segmentation_models/encoders/senet.py
segmentation_models/encoders/timm_efficientnet.py
segmentation_models/encoders/vgg.py
segmentation_models/encoders/xception.py
segmentation_models/unet/__init__.py
segmentation_models/unet/decoder.py
segmentation_models/unet/model.py
segmentation_models/utils/__init__.py
segmentation_models/utils/base.py
segmentation_models/utils/functional.py
segmentation_models/utils/losses.py
segmentation_models/utils/meter.py
segmentation_models/utils/metrics.py
segmentation_models/utils/train.py
mammopy-0.0.18.dist-info/LICENSE
mammopy-0.0.18.dist-info/METADATA
mammopy-0.0.18.dist-info/WHEEL
mammopy-0.0.18.dist-info/RECORD
